cxnet/__init__.py
cxnet/archives.py
cxnet/cc.py
cxnet/debnetworkc.py
cxnet/debnetworki.py
cxnet/debnetworkx.py
cxnet/decorators.py
cxnet/degdist.py
cxnet/igraphtools.py
cxnet/powerlaw.py
cxnet/revision.py
cxnet/system.py
cxnet/tools.py
cxnet-0.3.1.dist-info/AUTHORS
cxnet-0.3.1.dist-info/METADATA
cxnet-0.3.1.dist-info/WHEEL
cxnet-0.3.1.dist-info/top_level.txt
cxnet-0.3.1.dist-info/RECORD
