Metadata-Version: 2.1
Name: cxnet
Version: 0.3.1
Summary: Complex networks in education
Home-page: http://pyedu.hu/cxnet/doc/html
Author: Arpad Horvath
Author-email: horvath.arpad.szfvar@gmail.com
License: BSD License
Keywords: graph,network,mathematics,math,graph theory,discrete mathematics,complex networks
Platform: ALL
Classifier: Development Status :: 4 - Beta
Classifier: Intended Audience :: Education
Classifier: Intended Audience :: Science/Research
Classifier: Intended Audience :: Information Technology
Classifier: Intended Audience :: System Administrators
Classifier: Operating System :: OS Independent
Classifier: Programming Language :: Python
Classifier: Topic :: Scientific/Engineering
Classifier: Topic :: Scientific/Engineering :: Information Analysis
Classifier: Topic :: Scientific/Engineering :: Mathematics
Classifier: Topic :: Scientific/Engineering :: Physics
Classifier: Topic :: Software Development :: Libraries :: Python Modules
Classifier: License :: OSI Approved :: BSD License
